tictacsync/__init__.py
tictacsync/device_scanner.py
tictacsync/entry.py
tictacsync/mamconf.py
tictacsync/mamdav.py
tictacsync/mamreap.py
tictacsync/mamsync.py
tictacsync/multi2polywav.py
tictacsync/timeline.py
tictacsync/yaltc.py
tictacsync-1.5.2b0.dist-info/LICENSE
tictacsync-1.5.2b0.dist-info/METADATA
tictacsync-1.5.2b0.dist-info/WHEEL
tictacsync-1.5.2b0.dist-info/entry_points.txt
tictacsync-1.5.2b0.dist-info/top_level.txt
tictacsync-1.5.2b0.dist-info/RECORD
