Metadata-Version: 2.1
Name: tictacsync
Version: 1.5.2b0
Summary: commands for syncing audio video recordings
Home-page: https://tictacsync.org/
Author: Raymond Lutz
Author-email: lutzrayblog@mac.com
Classifier: Development Status :: 4 - Beta
Classifier: Environment :: Console
Classifier: Intended Audience :: End Users/Desktop
Classifier: License :: OSI Approved :: MIT License
Classifier: Operating System :: MacOS
Classifier: Operating System :: Microsoft :: Windows
Classifier: Operating System :: POSIX
Classifier: Programming Language :: Python :: 3
Classifier: Topic :: Multimedia :: Sound/Audio
Classifier: Topic :: Utilities
Classifier: Topic :: Multimedia :: Sound/Audio :: Capture/Recording
Classifier: Topic :: Multimedia :: Video :: Non-Linear Editor
Requires-Python: >=3.10
License-File: LICENSE
Requires-Dist: sox >=1.4.1
Requires-Dist: ffmpeg-python >=0.2.0
Requires-Dist: loguru >=0.6.0
Requires-Dist: matplotlib >=3.7.1
Requires-Dist: numpy >=1.24.3
Requires-Dist: rich >=10.12.0
Requires-Dist: lmfit
Requires-Dist: scikit-image
Requires-Dist: scipy >=1.10.1
Requires-Dist: platformdirs
